pywhistle/__init__.py
pywhistle/client.py
pywhistle-0.0.4.dist-info/LICENSE
pywhistle-0.0.4.dist-info/METADATA
pywhistle-0.0.4.dist-info/WHEEL
pywhistle-0.0.4.dist-info/top_level.txt
pywhistle-0.0.4.dist-info/RECORD
